{
  "slug": "AnimatedCircuits",
  "name": "Animated Circuits",
  "version": "1.0.0",
  "brand": "Animated Circuits",
  "author": "Animated Circuits",
  "license": "BSD-3-Clause",
  "authorEmail": "animatedcircuits@gmail.com",
  "pluginUrl": "https://github.com/AnimatedCircuits/RackModules/releases",
  "authorUrl": "https://www.animated-circuits.com",
  "manualUrl": "",
  "sourceUrl": "https://github.com/AnimatedCircuits/RackModules",
  "changelogUrl": "",
  "modules": [
    {
      "slug": "ACFolding",
      "name": "Folding",
      "description": "Wavefolder",
      "tags": [
        "Waveshaper"
      ]
    }
  ]
}