{
  "slug": "Autinn",
  "name": "Autinn",
  "version": "2.1.0",
  "license": "GPL-3.0-or-later",
  "brand": "Autinn",
  "author": "Nikolai V. Chr.",
  "authorEmail": "",
  "authorUrl": "",
  "pluginUrl": "",
  "manualUrl": "https://github.com/NikolaiVChr/Autinn/wiki",
  "sourceUrl": "https://github.com/NikolaiVChr/Autinn",
  "donateUrl": "https://www.paypal.me/autinn",
  "changelogUrl": "https://github.com/NikolaiVChr/Autinn/wiki/Changelog",
  "modules": [
    {
      "slug": "Amp",
      "name": "Amp",
      "description": "Amplifier",
      "tags": [
        "VCA",
        "Polyphonic",
        "Attenuator"
      ]
    },
    {
      "slug": "Bass",
      "name": "Bass",
      "description": "Bass and Acid synth",
      "tags": [
        "VCF",
        "Physical modeling"
      ]
    },
    {
      "slug": "Boomerang",
      "name": "Mera",
      "description": "Pre-post VCA",
      "tags": [
        "VCA",
        "Attenuator"
      ]
    },
    {
      "slug": "CVConverter",
      "name": "Conv",
      "description": "Converts to and from uni/bi CV voltages",
      "tags": [
        "Utility"
      ]
    },
    {
      "slug": "Deadband",
      "name": "Deadband",
      "description": "Constrain low voltages to zero",
      "tags": [
        "VCA",
        "Attenuator"
      ]
    },
    {
      "slug": "Digi",
      "name": "Digi",
      "description": "Quantizes a signal into discrete steps",
      "tags": [
        "Utility",
        "Digital",
        "Effect",
        "Quantizer",
        "Waveshaper"
      ]
    },
    {
      "slug": "Disee",
      "name": "DC",
      "description": "Outputs DC component of signal",
      "tags": [
        "Utility"
      ]
    },
    {
      "slug": "Flopper",
      "name": "Flopper",
      "description": "Mix signals in uncommon way",
      "tags": [
        "Waveshaper"
      ]
    },
    {
      "slug": "Jette",
      "name": "Jette",
      "description": "Oscillator with harmonics control",
      "tags": [
        "VCO"
      ]
    },
    {
      "slug": "Oxcart",
      "name": "Oxcart",
      "description": "Aggresive oscillator. Best for low/mid frequencies.",
      "tags": [
        "VCO"
      ]
    },
    {
      "slug": "Retri",
      "name": "Flora",
      "description": "A 24dB low-pass filter emulating a 4-pole transistor ladder",
      "tags": [
        "VCF",
        "Physical modeling",
        "Dual"
      ]
    },
    {
      "slug": "Saw",
      "name": "Saw",
      "description": "Oscillator with a sawish sound",
      "tags": [
        "VCO"
      ]
    },
    {
      "slug": "Sjip",
      "name": "Sjip",
      "description": "Oscillator with rounded waveform",
      "tags": [
        "VCO"
      ]
    },
    {
      "slug": "Square",
      "name": "Square",
      "description": "Oscillator with a squareish sound",
      "tags": [
        "VCO"
      ]
    },
    {
      "slug": "Vector",
      "name": "Vxy",
      "description": "Random x-y generator",
      "deprecated": true,
      "tags": [
        "Controller",
        "Utility",
        "Random"
      ]
    },
    {
      "slug": "Vibrato",
      "name": "Vibrato",
      "description": "Vibrato effect with optional Flanger",
      "tags": [
        "Effect",
        "Delay",
        "Flanger"
      ]
    },
    {
      "slug": "Zod",
      "name": "Zod",
      "description": "Dynamic range manipulator with noisegate",
      "tags": [
        "Compressor",
        "Limiter",
        "Dynamics",
        "Expander",
        "Dual"
      ]
    },
    {
      "slug": "TriBand",
      "name": "Imp",
      "description": "Simple Triple Band Equalizer",
      "tags": [
        "Equalizer"
      ]
    },
    {
      "slug": "Mixer6",
      "name": "6 Channel Mixer",
      "description": "6 channel mixer with no CV",
      "tags": [
        "Mixer",
        "Equalizer"
      ]
    },
    {
      "slug": "Non",
      "name": "Non",
      "description": "Limiter",
      "tags": [
        "Limiter",
        "Dynamics",
        "Dual"
      ]
    },
    {
      "slug": "Overdrive",
      "name": "Fil",
      "description": "Filing away at audio (Overdrive)",
      "tags": [
        "Effect",
        "Distortion"
      ]
    },
    {
      "slug": "Distortion",
      "name": "Nap",
      "description": "Taking a nap (Distortion)",
      "tags": [
        "Effect",
        "Distortion"
      ]
    },
    {
      "slug": "Melody",
      "name": "Fluencerator",
      "description": "Random melody sequencer with special constraints that make it sound more pleasant for the ear",
      "tags": [
        "Sequencer",
        "Random"
      ]
    },
    {
      "slug": "Chord",
      "name": "Rebel",
      "description": "Plays a random selected chord from a root note (does not have to be in tune). Polyphonic outputs.",
      "tags": [
        "Utility",
        "Polyphonic"
      ]
    }
  ]
}