{
  "slug": "MockbaModular",
  "name": "Mockba Modular",
  "version": "1.0.5",
  "license": "MIT",
  "brand": "Mockba Modular",
  "author": "Mockba the Borg",
  "authorEmail": "mockba.the.borg@gmail.com",
  "authorUrl": "http://mockbatheb.org/",
  "pluginUrl": "https://github.com/MockbaTheBorg/MockbaModular",
  "manualUrl": "https://github.com/MockbaTheBorg/MockbaModular/blob/master/README.md",
  "sourceUrl": "https://github.com/MockbaTheBorg/MockbaModular",
  "donateUrl": "http://paypal.me/MockbaTheBorg",
  "changelogUrl": "",
  "modules": [
    {
      "slug": "Blank",
      "name": "Blank",
      "description": "Simple blank",
      "tags": [
        "Blank"
      ]
    },
    {
      "slug": "Feidah",
      "name": "Feidah",
      "description": "Simple signal fader",
      "tags": [
        "Attenuator"
      ]
    },
    {
      "slug": "Mixah",
      "name": "Mixah",
      "description": "Simple two signal mixer",
      "tags": [
        "mixer"
      ]
    },
    {
      "slug": "Dividah",
      "name": "Dividah",
      "description": "Simple clock divider",
      "tags": [
        "Clock modulator"
      ]
    },
    {
      "slug": "Countah",
      "name": "Countah",
      "description": "Simple clock counter",
      "tags": [
        "Clock modulator"
      ]
    },
    {
      "slug": "Selectah",
      "name": "Selectah",
      "description": "Simple 4 to 1 selector",
      "tags": [
        "Utility"
      ]
    },
    {
      "slug": "UDPClockMaster",
      "name": "Mastah",
      "description": "UDP Clock Synchronizer (Master)",
      "tags": [
        "Utility"
      ]
    },
    {
      "slug": "UDPClockSlave",
      "name": "Slavah",
      "description": "UDP Clock Synchronizer (Slave)",
      "tags": [
        "Utility"
      ]
    }
  ]
}