{
  "slug": "VCV-Console",
  "name": "VCV Console",
  "version": "2.0.2",
  "license": "https://vcvrack.com/eula",
  "brand": "VCV",
  "author": "VCV",
  "authorEmail": "support@vcvrack.com",
  "authorUrl": "https://vcvrack.com/",
  "pluginUrl": "https://vcvrack.com/Console",
  "manualUrl": "https://vcvrack.com/Console#manual",
  "changelogUrl": "https://vcvrack.com/Console#changelog",
  "modules": [
    {
      "slug": "Console8_3",
      "name": "Console",
      "description": "8-channel stereo master mixer",
      "tags": [
        "Mixer"
      ]
    }
  ]
}