{
  "slug": "VCV-Pro",
  "name": "VCV Pro",
  "version": "2.0.2",
  "license": "proprietary",
  "brand": "VCV",
  "author": "VCV",
  "authorEmail": "support@vcvrack.com",
  "authorUrl": "https://vcvrack.com/",
  "pluginUrl": "https://vcvrack.com/Pro",
  "manualUrl": "https://vcvrack.com/Pro#manual",
  "sourceUrl": "",
  "donateUrl": "",
  "changelogUrl": "https://vcvrack.com/Pro#changelog",
  "modules": [
    {
      "slug": "Chorus",
      "name": "Chorus",
      "description": "",
      "manualUrl": "https://vcvrack.com/Pro#Chorus",
      "tags": [
        "Chorus",
        "Effect",
        "Polyphonic"
      ]
    },
    {
      "slug": "Flanger",
      "name": "Flanger",
      "description": "",
      "manualUrl": "https://vcvrack.com/Pro#Flanger",
      "tags": [
        "Flanger",
        "Effect",
        "Polyphonic"
      ]
    },
    {
      "slug": "Phaser",
      "name": "Phaser",
      "description": "",
      "manualUrl": "https://vcvrack.com/Pro#Phaser",
      "tags": [
        "Phaser",
        "Effect",
        "Polyphonic"
      ]
    }
  ]
}